[{"name":"elo_rating","evidenceType":"string","typeFidelity":"precise"},{"name":"team","evidenceType":"string","typeFidelity":"precise"},{"name":"conf","evidenceType":"string","typeFidelity":"precise"},{"name":"record","evidenceType":"string","typeFidelity":"precise"},{"name":"avg_wins","evidenceType":"number","typeFidelity":"precise"},{"name":"vegas_wins","evidenceType":"number","typeFidelity":"precise"},{"name":"elo_rating_1","evidenceType":"number","typeFidelity":"precise"},{"name":"elo_vs_vegas","evidenceType":"number","typeFidelity":"precise"},{"name":"win_range","evidenceType":"string","typeFidelity":"precise"},{"name":"seed_range","evidenceType":"string","typeFidelity":"precise"},{"name":"made_postseason","evidenceType":"number","typeFidelity":"precise"},{"name":"first_round_bye","evidenceType":"number","typeFidelity":"precise"},{"name":"sim_start_game_id","evidenceType":"number","typeFidelity":"precise"}]